testgres/postgres_configuration/__init__.py
testgres/postgres_configuration/abstract/v00/configuration.py
testgres/postgres_configuration/core/bugcheck_error.py
testgres/postgres_configuration/core/controller_utils.py
testgres/postgres_configuration/core/data_verificator.py
testgres/postgres_configuration/core/handlers.py
testgres/postgres_configuration/core/helpers.py
testgres/postgres_configuration/core/model.py
testgres/postgres_configuration/core/raise_error.py
testgres/postgres_configuration/core/read_utils.py
testgres/postgres_configuration/core/write_utils.py
testgres/postgres_configuration/core/option/handlers/add/option_handler_to_add__std.py
testgres/postgres_configuration/core/option/handlers/get_value/option_handler_to_get_value__std__simple.py
testgres/postgres_configuration/core/option/handlers/get_value/option_handler_to_get_value__std__union_list.py
testgres/postgres_configuration/core/option/handlers/prepare_get_value/option_handler_to_prepare_get_value__std__bool.py
testgres/postgres_configuration/core/option/handlers/prepare_get_value/option_handler_to_prepare_get_value__std__generic.py
testgres/postgres_configuration/core/option/handlers/prepare_get_value/option_handler_to_prepare_get_value__std__int.py
testgres/postgres_configuration/core/option/handlers/prepare_get_value/option_handler_to_prepare_get_value__std__str.py
testgres/postgres_configuration/core/option/handlers/prepare_get_value/option_handler_to_prepare_get_value__std__unique_str_list.py
testgres/postgres_configuration/core/option/handlers/prepare_set_value/option_handler_to_prepare_set_value__std__bool.py
testgres/postgres_configuration/core/option/handlers/prepare_set_value/option_handler_to_prepare_set_value__std__generic.py
testgres/postgres_configuration/core/option/handlers/prepare_set_value/option_handler_to_prepare_set_value__std__int.py
testgres/postgres_configuration/core/option/handlers/prepare_set_value/option_handler_to_prepare_set_value__std__str.py
testgres_postgres_configuration-0.2.0.dist-info/licenses/LICENSE
testgres_postgres_configuration-0.2.0.dist-info/METADATA
testgres_postgres_configuration-0.2.0.dist-info/WHEEL
testgres_postgres_configuration-0.2.0.dist-info/top_level.txt
testgres_postgres_configuration-0.2.0.dist-info/RECORD
